{
    "name": "Department",
    "fields": [
        {
            "fieldName": "departmentName",
            "fieldType": "String",
            "fieldValidateRules": [
                "required"
            ]
        }
    ],
    "relationships": [
        {
            "relationshipType": "one-to-many",
            "javadoc": "A relationship",
            "relationshipName": "employee",
            "otherEntityName": "employee",
            "otherEntityRelationshipName": "department"
        },
        {
            "relationshipType": "many-to-one",
            "relationshipName": "location",
            "otherEntityName": "location",
            "otherEntityField": "streetAddress"
        }
    ],
    "changelogDate": "20181202064618",
    "entityTableName": "department",
    "dto": "mapstruct",
    "pagination": "no",
    "service": "serviceClass",
    "jpaMetamodelFiltering": false,
    "fluentMethods": true,
    "clientRootFolder": "",
    "applications": [
        "jhipster"
    ]
}